{
    "MONGO_DATABASE_URL" : "mongodb://lendenclub:8g38n8AbgKbdUPYP@3.109.177.215:27017/?&tls=false",
    "MONGO_DBNAME" : "bsas",

    "AWS_ACCESS_KEY_ID" : "AKIAJKZFYGY2CFB6WF6Q",
    "AWS_SECRET_ACCESS_KEY" : "+e0N+bXyLFDrO4k8gHI0ICdRjT\/8\/ROlg533hzmw",
    "AWS_STORAGE_BUCKET_NAME" : "lendendocs",
    "AWS_BUCKET_POSTFIX" : "media/documents",
    "MONO_AUTH_TOKEN" : "PYT9EwhwtRGyRq2RfiwqqrxzOLTp77r1BvXFi2IKvnHbGjLoKNF2iWw6jrQfH.aEBakazUrMJHvpBUcyZaaVM8ORcQwaUSeZmihlP5Zv3bSGYYV8J8tb8jrNN9D.DQAYeEtIhAHRWn91OeehAP4FVBBGMjCqzeazt02UazlH18LdcQeRTNHhrkPP9",

    "FINORAMIC_CLIENT_ID" : "sandbox1-cf7c-4ada-a641-c24910c3f91b",
    "FINORAMIC_CLENT_SERVICE" : "sandbox1-0fe5-46ef-9bb0-a191e811248a",
    "FINORAMIC_APPLICATION_ID" : "421e283941b55b44e5177e029a4e65a5",
    "FINORAMIC_BANKSTATEMENT_DOWNLOAD_URL" : "https://sandbox.finoramic.com/parse/functions/client_getConsolidatedData",
    "FINORAMIC_APP_REDIRECT_URL" : "https://instamoney.page.link/zMkSMorSJxLadU8G6",
    "FINORAMIC_REFRESH_API" : "https://sandbox.finoramic.com/parse/functions/client_refreshUserData",
    "FINORAMIC_REDIRECT_MONO_NOTIFY" : true,
    "FINORAMIC_REPORT_MONO_NOTIFY" : true,

    "MONO_NOTIFY_LOGIN_URL" : "https://qa.lendenclub.com/core/instamoney/v3/update-finoramic-login-status",
    "SEND_STATEMENT_REPORT_URL" : "https://qa.lendenclub.com/core/instamoney/v3/post-finoramic-salary-info",

    "GLIB_AUTH_TOKEN" : "eyJ0eXAiOiJKV1QiLCJhbGciOiJIUzI1NiJ9.eyJleHAiOjE2ODQ4MjMzMjYsImlhdCI6MTY1MzI4NzMyNiwib3JnYW5pemF0aW9uIjoiTVdad3FjNXA2QXdVVHlkZnNyMHciLCJ1aWQiOiJpaFdRR1JOMTdWZURuRENTOXVocnQ3a1lGVzgzIiwicm9sZSI6ImFkbWluIn0.gIfY-vs6PfVQjmqhXfsD-0K2Vis7otJRYCjWrSr32ZQ",
    "GLIB_UPLOAD_BANKSTATEMENT_URL" : "https://process-workorders.auto-sift.com",
    "GLIB_ANALISYS_DOWNLOAD_URL" : "https://download-report.auto-sift.com",
    "GLIB_SERVICE_NAME" : "glib",
    "GLIB_UPLOAD_API_NAME" : "glib_upload",
    "GLIB_ANALYSIS_API_NAME" : "glib_download",
    "GLIB_STATUS_API_NAME" : "glib_status",
    "GLIB_UPLOAD_REQUEST_SUBMIT" : "Request has been submitted to GLIB",
    "GLIB_FIX_WAIT_DOWNLOADREPORT" : 10,
    "GLIB_VALID_SALARY_MODE" : ["ACH","ECS","Cheque","NEFT","RTGS","UPI","Internet Banking","Mobile Banking","Cash","POS","IMPS","DEMAND DRAFT","RTGS INWARD","RTGS OUTWARD","ATL","ATM","EAW","NWD","PCD","Payment Gateway"],
    "GLIB_CALLBACK_PROCESS_COMPLETE" : "SUCCESS",
    "GLIB_CALLBACK_PROCESS_FAIL" : "FAILURE",
    "GLIB_MONO_NOTIFY" : true,
    "MONO_SEND_DATA_JSON_URL" : "https://qa.lendenclub.com/glib/store-salary-data/",
    "MONO_SEND_DATA_EXCEL_URL" : "https://qa.lendenclub.com/glib/store-statement-report/",

    "PIRIMID_ORGANIZATION_ID" : "PIR0770",
    "PIRIMID_CLIENT_ID" : "fp_test_767fcc32e98cba073b70d9af70242ac7d10c3f29",
    "PIRIMID_CLIENT_SECRET" : "9f6d72bdb6f57d08b09000623ec7d0a110b0fbf4a7dd69ca927b2f5678903e561d749ba9",
    "PIRMID_BASE_URL" : "https://api-sandbox.onemoney.in/",
    "PIRMID_FIP_ID" : "finsharebank",
    "PIRMID_FIP_NAME" : "FinShareBank Server",
    "PIRMID_ONE_MONEY_BASE_URL" : "https://api-sandbox.onemoney.in",
    "PIRMID_API_KEY" : "AaNa8c04z8",
    "PIRIMID_SERVICE_NAME" : "pirimid",
    "PIRIMID_BASE_URL" : "http://43.204.48.149:8080",
    "PIRIMID_INITIATE_URL" : "http://43.204.48.149:8080/api/web/initiate",
    "PIRIMID_MONO_INITIATE_WITH_REDIRECTION" : "http://43.204.48.149:8080/api/web/initiate-redirection",
    "PIRIMID_REDIRECT_URL" : "http://localhost:5000/web/redirect/handler",
    "PIRMID_FIP_URL" : "http://43.204.48.149:8080/api/web/fip",
    "PIRIMID_JSON_DOWNLOAD_URL" : "http://43.204.48.149:8080/api/web/fetch/analytics/json",
    "PIRIMID_EXCEL_DOWNLOAD_URL" : "http://43.204.48.149:8080/api/web/fetch/analytics/excel",
    "PIRIMID_DECRYPT_URL" : "http://43.204.48.149:8080/api/web/decrypt-redirect",
    "PIRIMID_VUA_URL" : "http://43.204.153.135:8091/fiu/api/web/vuaId",
    "PIRIMID_MONO_JSON_DATA_URL" : "https://qa.lendenclub.com/pirimid/store-banking-data/",
    "PIRIMID_MONO_EXCEL_DATA_URL" : "https://qa.lendenclub.com/pirimid/store-excel-report/",
    "PIRIMID_STATUS_REDIRECT_URL" : "https://instamoney.page.link/h77c",
    "PIRIMID_WEBHOOK_AUTH_TOKEN" : "Xn2r5u8x/A?D(G+KaPdSgVkYp3s6v9y$B&E)H@McQeThWmZq4t7w!z%C*F-JaNd",
    "PIRIMID_SPOT_REDIRECT_FAILURE_URL" : "https://www.instamoney.app/pirimid-failure-spot/",
    "PIRIMID_SPOT_REDIRECT_SUCCESS_URL" : "https://www.instamoney.app/pirimid-success-spot/"
}